MANIFEST.in
README.rst
setup.py
auromat/__init__.py
auromat/_version.py
auromat/debug.py
auromat/draw.py
auromat/draw_helpers.py
auromat/fits.py
auromat/resample.py
auromat/utils.py
auromat.egg-info/PKG-INFO
auromat.egg-info/SOURCES.txt
auromat.egg-info/dependency_links.txt
auromat.egg-info/entry_points.txt
auromat.egg-info/requires.txt
auromat.egg-info/top_level.txt
auromat/cli/__init__.py
auromat/cli/convert.py
auromat/cli/download.py
auromat/coordinates/__init__.py
auromat/coordinates/constellations.py
auromat/coordinates/ephem.py
auromat/coordinates/geodesic.py
auromat/coordinates/igrf.py
auromat/coordinates/intersection.py
auromat/coordinates/spacetrack.py
auromat/coordinates/transform.py
auromat/coordinates/transformations.py
auromat/coordinates/wcs.py
auromat/export/__init__.py
auromat/export/_gdal.py
auromat/export/cdf.py
auromat/export/netcdf.py
auromat/mapping/__init__.py
auromat/mapping/astrometry.py
auromat/mapping/cdf.py
auromat/mapping/iss.py
auromat/mapping/mapping.py
auromat/mapping/miracle.py
auromat/mapping/netcdf.py
auromat/mapping/spacecraft.py
auromat/mapping/themis.py
auromat/resources/__init__.py
auromat/resources/ne_10m_populated_places_simple.dbf
auromat/resources/ne_10m_populated_places_simple.shp
auromat/resources/ne_10m_populated_places_simple.shx
auromat/resources/ne_50m_populated_places_simple.dbf
auromat/resources/ne_50m_populated_places_simple.shp
auromat/resources/ne_50m_populated_places_simple.shx
auromat/solving/__init__.py
auromat/solving/eol.py
auromat/solving/masking.py
auromat/solving/noiseestimation.py
auromat/solving/solving.py
auromat/solving/spacecraft.py
auromat/solving/viewasblocks.py
auromat/test/__init__.py
auromat/test/benchmark.py
auromat/test/boundingbox_test.py
auromat/test/draw_test.py
auromat/test/elevation_test.py
auromat/test/export_cdf_test.py
auromat/test/export_netcdf_test.py
auromat/test/geodesic_test.py
auromat/test/intersection_test.py
auromat/test/iss_provider_test.py
auromat/test/lensdistortion_test.py
auromat/test/mapping_test.py
auromat/test/movie_test.py
auromat/test/mpl_leak.py
auromat/test/outline_test.py
auromat/test/profiling.py
auromat/test/resample_test.py
