Metadata-Version: 1.1
Name: auromat
Version: 1.0.5
Summary: AUROra MApping Toolkit
Home-page: https://github.com/esa/auromat
Author: Maik Riechert
Author-email: mriecher@cosmos.esa.int, awalsh@sciops.esa.int
License: ESCL - Type 1
Platform: UNKNOWN
Classifier: Development Status :: 5 - Production/Stable
Classifier: Intended Audience :: Science/Research
Classifier: Natural Language :: English
Classifier: Programming Language :: Python :: 2
Classifier: Programming Language :: Python :: 3
Classifier: Operating System :: OS Independent
Classifier: Topic :: Scientific/Engineering
Classifier: Topic :: Software Development :: Libraries
